airclick/__init__.py
airclick/android/__init__.py
airclick/android/data.py
airclick/android/action/__init__.py
airclick/android/action/gesture.py
airclick/android/action/key.py
airclick/android/action/path.py
airclick/android/action/touch.py
airclick/android/graphics/__init__.py
airclick/android/intent/__init__.py
airclick/android/node/__init__.py
airclick/android/node/node.py
airclick/android/screen/__init__.py
airclick/android/system/Prgogress.py
airclick/android/system/__init__.py
airclick/android/ui/__init__.py
airclick/android/ui/dialog.py
airclick/windows/__init__.py
airclick/windows/action.py
airclick/windows/screen.py
airclick/windows/system.py
airclick/windows/window.py
airclick/windows/client/__init__.py
airclick/windows/client/server.py
airclick/windows/client/start.py
airclick/windows/client/tools.py
airclick/windows/client/ui.py
airclick/windows/client/worker.py
airclick/windows/client/assets/__init__.py
airclick/windows/client/assets/bootstrap-4.6.2-dist/css/bootstrap-grid.css
airclick/windows/client/assets/bootstrap-4.6.2-dist/css/bootstrap-grid.css.map
airclick/windows/client/assets/bootstrap-4.6.2-dist/css/bootstrap-grid.min.css
airclick/windows/client/assets/bootstrap-4.6.2-dist/css/bootstrap-grid.min.css.map
airclick/windows/client/assets/bootstrap-4.6.2-dist/css/bootstrap-reboot.css
airclick/windows/client/assets/bootstrap-4.6.2-dist/css/bootstrap-reboot.css.map
airclick/windows/client/assets/bootstrap-4.6.2-dist/css/bootstrap-reboot.min.css
airclick/windows/client/assets/bootstrap-4.6.2-dist/css/bootstrap-reboot.min.css.map
airclick/windows/client/assets/bootstrap-4.6.2-dist/css/bootstrap.css
airclick/windows/client/assets/bootstrap-4.6.2-dist/css/bootstrap.css.map
airclick/windows/client/assets/bootstrap-4.6.2-dist/css/bootstrap.min.css
airclick/windows/client/assets/bootstrap-4.6.2-dist/css/bootstrap.min.css.map
airclick/windows/client/assets/bootstrap-4.6.2-dist/js/bootstrap.bundle.js
airclick-0.0.3.26.dist-info/METADATA
airclick-0.0.3.26.dist-info/WHEEL
airclick-0.0.3.26.dist-info/top_level.txt
airclick-0.0.3.26.dist-info/RECORD
