Metadata-Version: 2.1
Name: airclick
Version: 0.0.3.26
Summary: airclick 相关python包
Home-page: https://airscript.cn/
Author: aojoy
Author-email: aojoytec@163.com
License: MIT
Keywords: python,airclick
Classifier: Programming Language :: Python :: 3
Classifier: License :: OSI Approved :: MIT License
Classifier: Operating System :: OS Independent
Requires-Dist: anyio ==4.2.0
Requires-Dist: astor ==0.8.1
Requires-Dist: attrdict ==2.0.1
Requires-Dist: Babel ==2.14.0
Requires-Dist: bce-python-sdk ==0.8.98
Requires-Dist: beautifulsoup4 ==4.12.2
Requires-Dist: blinker ==1.7.0
Requires-Dist: cachetools ==5.3.2
Requires-Dist: certifi ==2023.11.17
Requires-Dist: cffi ==1.16.0
Requires-Dist: charset-normalizer ==3.3.2
Requires-Dist: click ==8.1.7
Requires-Dist: colorama ==0.4.6
Requires-Dist: contourpy ==1.1.1
Requires-Dist: cssselect ==1.2.0
Requires-Dist: cssutils ==2.9.0
Requires-Dist: cycler ==0.12.1
Requires-Dist: Cython ==3.0.7
Requires-Dist: decorator ==5.1.1
Requires-Dist: docutils ==0.20.1
Requires-Dist: et-xmlfile ==1.1.0
Requires-Dist: exceptiongroup ==1.2.0
Requires-Dist: fire ==0.5.0
Requires-Dist: Flask ==3.0.0
Requires-Dist: flask-babel ==4.0.0
Requires-Dist: fonttools ==4.47.0
Requires-Dist: future ==0.18.3
Requires-Dist: gevent ==23.9.1
Requires-Dist: greenlet ==3.0.3
Requires-Dist: h11 ==0.14.0
Requires-Dist: httpcore ==1.0.2
Requires-Dist: httpx ==0.26.0
Requires-Dist: idna ==3.6
Requires-Dist: imageio ==2.33.1
Requires-Dist: imgaug ==0.4.0
Requires-Dist: importlib-metadata ==7.0.1
Requires-Dist: importlib-resources ==6.1.1
Requires-Dist: itsdangerous ==2.1.2
Requires-Dist: jaraco.classes ==3.3.0
Requires-Dist: Jinja2 ==3.1.2
Requires-Dist: keyring ==24.3.0
Requires-Dist: kiwisolver ==1.4.5
Requires-Dist: lazy-loader ==0.3
Requires-Dist: lmdb ==1.4.1
Requires-Dist: lxml ==5.0.0
Requires-Dist: markdown-it-py ==3.0.0
Requires-Dist: MarkupSafe ==2.1.3
Requires-Dist: matplotlib ==3.7.4
Requires-Dist: mdurl ==0.1.2
Requires-Dist: more-itertools ==10.1.0
Requires-Dist: MouseInfo ==0.1.3
Requires-Dist: networkx ==3.1
Requires-Dist: nh3 ==0.2.15
Requires-Dist: numpy ==1.24.4
Requires-Dist: opencv-contrib-python ==4.6.0.66
Requires-Dist: opencv-python ==4.6.0.66
Requires-Dist: openpyxl ==3.1.2
Requires-Dist: opt-einsum ==3.3.0
Requires-Dist: packaging ==23.2
Requires-Dist: paddleocr ==2.7.0.3
Requires-Dist: paddlepaddle ==2.6.0
Requires-Dist: pandas ==2.0.3
Requires-Dist: pdf2docx ==0.5.5
Requires-Dist: pillow ==10.2.0
Requires-Dist: pkginfo ==1.9.6
Requires-Dist: premailer ==3.10.0
Requires-Dist: protobuf ==3.20.2
Requires-Dist: psutil ==5.9.7
Requires-Dist: PyAutoGUI ==0.9.54
Requires-Dist: pyclipper ==1.3.0.post5
Requires-Dist: pycparser ==2.21
Requires-Dist: pycryptodome ==3.19.1
Requires-Dist: PyGetWindow ==0.0.9
Requires-Dist: Pygments ==2.17.2
Requires-Dist: PyMsgBox ==1.0.9
Requires-Dist: PyMuPDF ==1.20.2
Requires-Dist: pyparsing ==3.1.1
Requires-Dist: pyperclip ==1.8.2
Requires-Dist: PyQt5 ==5.15.10
Requires-Dist: PyQt5-Qt5 ==5.15.2
Requires-Dist: PyQt5-sip ==12.13.0
Requires-Dist: PyRect ==0.2.0
Requires-Dist: PyScreeze ==0.1.30
Requires-Dist: python-dateutil ==2.8.2
Requires-Dist: python-docx ==1.1.0
Requires-Dist: pytweening ==1.0.7
Requires-Dist: pytz ==2023.3.post1
Requires-Dist: PyWavelets ==1.4.1
Requires-Dist: pywin32 ==306
Requires-Dist: pywin32-ctypes ==0.2.2
Requires-Dist: PyYAML ==6.0.1
Requires-Dist: rapidfuzz ==3.6.1
Requires-Dist: rarfile ==4.1
Requires-Dist: readme-renderer ==42.0
Requires-Dist: requests ==2.31.0
Requires-Dist: requests-toolbelt ==1.0.0
Requires-Dist: rfc3986 ==2.0.0
Requires-Dist: rich ==13.7.0
Requires-Dist: scikit-image ==0.21.0
Requires-Dist: scipy ==1.10.1
Requires-Dist: shapely ==2.0.2
Requires-Dist: six ==1.16.0
Requires-Dist: sniffio ==1.3.0
Requires-Dist: soupsieve ==2.5
Requires-Dist: termcolor ==2.4.0
Requires-Dist: tifffile ==2023.7.10
Requires-Dist: tqdm ==4.66.1
Requires-Dist: twine ==4.0.2
Requires-Dist: typing-extensions ==4.9.0
Requires-Dist: tzdata ==2023.4
Requires-Dist: urllib3 ==2.1.0
Requires-Dist: visualdl ==2.5.3
Requires-Dist: websocket-client ==1.7.0
Requires-Dist: Werkzeug ==3.0.1
Requires-Dist: WMI ==1.5.1
Requires-Dist: zipp ==3.17.0
Requires-Dist: zope.event ==5.0
Requires-Dist: zope.interface ==6.1
